hello_world/__init__.py
hello_world/another-file.py
hello_world/another.py
hello_world/main.py
hello_world_arturgudiev-0.0.9.dist-info/LICENSE
hello_world_arturgudiev-0.0.9.dist-info/METADATA
hello_world_arturgudiev-0.0.9.dist-info/WHEEL
hello_world_arturgudiev-0.0.9.dist-info/top_level.txt
hello_world_arturgudiev-0.0.9.dist-info/RECORD
